nanohub_dashboards-0.1.4.dist-info/licenses/LICENSE
nanohubdashboard/__init__.py
nanohubdashboard/__version__.py
nanohubdashboard/client.py
nanohubdashboard/config.py
nanohubdashboard/dashboard.py
nanohubdashboard/datasource.py
nanohubdashboard/exceptions.py
nanohubdashboard/graph.py
nanohubdashboard/plot.py
nanohubdashboard/query.py
nanohubdashboard/template.py
nanohubdashboard/utils.py
tests/__init__.py
tests/conftest.py
tests/test_client.py
tests/test_config.py
tests/test_dashboard.py
tests/test_graph.py
tests/test_grouping.py
tests/test_plot.py
tests/test_query_authorization.py
tests/test_template_parsing.py
tests/test_utils.py
nanohub_dashboards-0.1.4.dist-info/METADATA
nanohub_dashboards-0.1.4.dist-info/WHEEL
nanohub_dashboards-0.1.4.dist-info/top_level.txt
nanohub_dashboards-0.1.4.dist-info/RECORD
