Metadata-Version: 2.4
Name: nanohub-dashboards
Version: 0.1.4
Summary: Python client library for interacting with the nanoHUB Dashboard API
Home-page: https://github.com/denphi/nanohub-dashboards
Author: nanoHUB
Author-email: nanoHUB <support@nanohub.org>
License: MIT
Project-URL: Homepage, https://nanohub.org
Project-URL: Repository, https://github.com/denphi/nanohub-dashboards
Project-URL: Documentation, https://github.com/denphi/nanohub-dashboards#readme
Project-URL: Issues, https://github.com/denphi/nanohub-dashboards/issues
Keywords: nanohub,dashboard,visualization,plotly
Classifier: Development Status :: 3 - Alpha
Classifier: Intended Audience :: Developers
Classifier: Intended Audience :: Science/Research
Classifier: Programming Language :: Python :: 3
Classifier: Programming Language :: Python :: 3.6
Classifier: Programming Language :: Python :: 3.7
Classifier: Programming Language :: Python :: 3.8
Classifier: Programming Language :: Python :: 3.9
Classifier: Programming Language :: Python :: 3.10
Classifier: Programming Language :: Python :: 3.11
Requires-Python: >=3.6
License-File: LICENSE
Requires-Dist: requests
Requires-Dist: plotly
Requires-Dist: pandas
Requires-Dist: nanohub-remote
Provides-Extra: test
Requires-Dist: pytest>=7.0; extra == "test"
Requires-Dist: pytest-cov>=4.0; extra == "test"
Requires-Dist: pytest-mock>=3.10; extra == "test"
Requires-Dist: responses>=0.22; extra == "test"
Provides-Extra: docs
Requires-Dist: sphinx>=5.0; extra == "docs"
Requires-Dist: sphinx-rtd-theme>=1.2; extra == "docs"
Requires-Dist: sphinx-autodoc-typehints>=1.19; extra == "docs"
Provides-Extra: dev
Requires-Dist: nanohub-dashboards[docs,test]; extra == "dev"
Dynamic: author
Dynamic: home-page
Dynamic: license-file
Dynamic: requires-python
